serverless_psycopg2/__init__.py
serverless_psycopg2/event.py
serverless_psycopg2/pg2_wrapper.py
serverless_psycopg2/test_serverless_pg2.py
serverless_psycopg2-0.0.2.dist-info/LICENSE
serverless_psycopg2-0.0.2.dist-info/METADATA
serverless_psycopg2-0.0.2.dist-info/WHEEL
serverless_psycopg2-0.0.2.dist-info/top_level.txt
serverless_psycopg2-0.0.2.dist-info/RECORD
