Metadata-Version: 2.1
Name: serverless-psycopg2
Version: 0.0.2
Summary: psycopg2 wrapper intended to be used in aws lambda
Home-page: https://gitlab.com/point1304/serverless-psycopg2
Author: Gyeongsu Yim
Author-email: point1304@gmail.com
License: UNKNOWN
Platform: UNKNOWN
Classifier: Programming Language :: Python :: 3
Classifier: License :: OSI Approved :: MIT License
Classifier: Operating System :: OS Independent
Requires-Python: >=3.6
Requires-Dist: psycopg2-binary (>=2.8.4)
